fractal_repositories/__init__.py
fractal_repositories/exceptions.py
fractal_repositories/py.typed
fractal_repositories/contrib/__init__.py
fractal_repositories/contrib/django/__init__.py
fractal_repositories/contrib/django/mixins.py
fractal_repositories/contrib/duckdb/__init__.py
fractal_repositories/contrib/duckdb/mixins.py
fractal_repositories/contrib/gcp/__init__.py
fractal_repositories/contrib/gcp/cloudstorage/__init__.py
fractal_repositories/contrib/gcp/cloudstorage/mixins.py
fractal_repositories/contrib/gcp/firestore/__init__.py
fractal_repositories/contrib/gcp/firestore/mixins.py
fractal_repositories/contrib/mongo/__init__.py
fractal_repositories/contrib/mongo/mixins.py
fractal_repositories/contrib/postgresql/__init__.py
fractal_repositories/contrib/postgresql/mixins.py
fractal_repositories/contrib/sqlalchemy/__init__.py
fractal_repositories/contrib/sqlalchemy/mixins.py
fractal_repositories/core/__init__.py
fractal_repositories/core/entity.py
fractal_repositories/core/repositories.py
fractal_repositories/mixins/__init__.py
fractal_repositories/mixins/external_data_inmemory_repository_mixin.py
fractal_repositories/mixins/file_repository_mixin.py
fractal_repositories/mixins/filter_repository_mixin.py
fractal_repositories/mixins/inmemory_repository_mixin.py
fractal_repositories/utils/__init__.py
fractal_repositories/utils/cached_repository.py
fractal_repositories/utils/distributed_read_repository.py
fractal_repositories/utils/json_encoder.py
fractal_repositories-1.3.1.dist-info/licenses/LICENSE
fractal_repositories-1.3.1.dist-info/WHEEL
fractal_repositories-1.3.1.dist-info/METADATA
fractal_repositories-1.3.1.dist-info/RECORD
