Metadata-Version: 2.4
Name: fractal-repositories
Version: 1.3.1
Summary: Fractal Repositories is an implementation of the repository pattern of Domain Driven Design (DDD) for building SOLID logic for your Python applications.
Keywords: database,query,projection,aggregation,sql,mongodb,firestore,elasticsearch
Author-email: Douwe van der Meij <douwe@karibu-online.nl>
Requires-Python: >=3.10
Classifier: Development Status :: 3 - Alpha
Classifier: Intended Audience :: Developers
Classifier: License :: OSI Approved :: MIT License
Classifier: Programming Language :: Python :: 3
Classifier: Programming Language :: Python :: 3.10
Classifier: Programming Language :: Python :: 3.11
Classifier: Programming Language :: Python :: 3.12
Classifier: Programming Language :: Python :: 3.13
Classifier: Programming Language :: Python :: 3.14
Classifier: Topic :: Software Development :: Libraries :: Python Modules
Classifier: Topic :: Database
License-File: LICENSE
Requires-Dist: fractal-specifications
Requires-Dist: django>=5.2.7 ; extra == "all"
Requires-Dist: duckdb>=0.9.0 ; extra == "all"
Requires-Dist: google-cloud-firestore>=2.0.0 ; extra == "all"
Requires-Dist: psycopg2-binary>=2.9.0 ; extra == "all"
Requires-Dist: pymongo>=4.0.0 ; extra == "all"
Requires-Dist: sqlalchemy>=2.0 ; extra == "all"
Requires-Dist: django>=5.2.7 ; extra == "dev"
Requires-Dist: duckdb>=0.9.0 ; extra == "dev"
Requires-Dist: pytest<8 ; extra == "dev"
Requires-Dist: pytest-cov>=4.0.0 ; extra == "dev"
Requires-Dist: black>=23.0.0 ; extra == "dev"
Requires-Dist: ruff>=0.1.0 ; extra == "dev"
Requires-Dist: mypy>=1.0.0 ; extra == "dev"
Requires-Dist: isort>=5.13.2 ; extra == "dev"
Requires-Dist: sqlalchemy>=2.0 ; extra == "dev"
Requires-Dist: mock-firestore>=0.11.0 ; extra == "dev"
Requires-Dist: cloud-storage-mocker>=0.3.4 ; extra == "dev"
Requires-Dist: pymongo>=4.0.0 ; extra == "dev"
Requires-Dist: mongomock>=4.3.0 ; extra == "dev"
Requires-Dist: pydantic>=2.12.3 ; extra == "dev"
Requires-Dist: pytest-mock>=3.15.1 ; extra == "dev"
Requires-Dist: firebase-admin>=7.1.0 ; extra == "dev"
Requires-Dist: psycopg2-binary>=2.9.0 ; extra == "dev"
Requires-Dist: django>=5.2.7 ; extra == "django"
Requires-Dist: duckdb>=0.9.0 ; extra == "duckdb"
Requires-Dist: google-cloud-firestore>=2.0.0 ; extra == "firestore"
Requires-Dist: pymongo>=4.0.0 ; extra == "mongo"
Requires-Dist: psycopg2-binary>=2.9.0 ; extra == "postgres"
Requires-Dist: sqlalchemy>=2.0 ; extra == "sqlalchemy"
Project-URL: Documentation, https://github.com/douwevandermeij/fractal-repositories#readme
Project-URL: Homepage, https://github.com/douwevandermeij/fractal-repositories
Project-URL: Issues, https://github.com/douwevandermeij/fractal-repositories/issues
Project-URL: Repository, https://github.com/douwevandermeij/fractal-repositories
Provides-Extra: all
Provides-Extra: dev
Provides-Extra: django
Provides-Extra: duckdb
Provides-Extra: firestore
Provides-Extra: mongo
Provides-Extra: postgres
Provides-Extra: sqlalchemy
